Metadata-Version: 1.1
Name: django-private-files
Version: 1.0.1
Summary: Protected files in django
Home-page: https://github.com/vvangelovski/django-private-files
Author: Vasil Vangelovski
Author-email: vvangelovski@gmail.com
License: New BSD License (http://www.opensource.org/licenses/bsd-license.php)
Platform: UNKNOWN
Classifier: Development Status :: 4 - Beta
Classifier: Environment :: Plugins
Classifier: Framework :: Django
Classifier: Intended Audience :: Developers
Classifier: License :: OSI Approved :: BSD License
Classifier: Topic :: Software Development :: Libraries :: Python Modules
Classifier: Programming Language :: Python :: 2.7
Classifier: Programming Language :: Python :: 3.5
Classifier: Programming Language :: Python :: 3.6
